reader/__init__.py
reader/__main__.py
reader/config.txt
reader/feed.py
reader/viewer.py
thanhle_realpython_reader-1.0.0.dist-info/METADATA
thanhle_realpython_reader-1.0.0.dist-info/WHEEL
thanhle_realpython_reader-1.0.0.dist-info/entry_points.txt
thanhle_realpython_reader-1.0.0.dist-info/top_level.txt
thanhle_realpython_reader-1.0.0.dist-info/RECORD
